README
flask_psycopg2.py
setup.py
Flask_Psycopg2.egg-info/PKG-INFO
Flask_Psycopg2.egg-info/SOURCES.txt
Flask_Psycopg2.egg-info/dependency_links.txt
Flask_Psycopg2.egg-info/not-zip-safe
Flask_Psycopg2.egg-info/requires.txt
Flask_Psycopg2.egg-info/top_level.txt