Metadata-Version: 1.1
Name: Flask-Psycopg2
Version: 1.0
Summary: postgresql adapter for Flask
Home-page: http://example.com/flask-psycopg2/
Author: Stefan Brink
Author-email: brefan@gmail.com
License: Public Domain
Platform: any
Classifier: Environment :: Web Environment
Classifier: Intended Audience :: Developers
Classifier: License :: Public Domain
Classifier: Operating System :: OS Independent
Classifier: Programming Language :: Python
Classifier: Topic :: Internet :: WWW/HTTP :: Dynamic Content
Classifier: Topic :: Software Development :: Libraries :: Python Modules
